imlightgbm/__init__.py
imlightgbm/base.py
imlightgbm/docstring.py
imlightgbm/engine.py
imlightgbm/objective/__init__.py
imlightgbm/objective/core.py
imlightgbm/objective/engine.py
imlightgbm/sklearn.py
imlightgbm/utils.py
imlightgbm-0.1.0.dist-info/LICENSE
imlightgbm-0.1.0.dist-info/METADATA
imlightgbm-0.1.0.dist-info/WHEEL
imlightgbm-0.1.0.dist-info/RECORD
