Metadata-Version: 2.1
Name: imlightgbm
Version: 0.1.0
Summary: LightGBM for label-imbalanced data with focal and weighted loss function
Home-page: https://github.com/RektPunk/Imbalance-LightGBM
License: MIT
Author: RektPunk
Author-email: rektpunk@gmail.com
Requires-Python: >=3.10,<4.0
Classifier: License :: OSI Approved :: MIT License
Classifier: Programming Language :: Python :: 3
Classifier: Programming Language :: Python :: 3.10
Classifier: Programming Language :: Python :: 3.11
Classifier: Programming Language :: Python :: 3.12
Classifier: Topic :: Software Development :: Libraries :: Python Modules
Requires-Dist: lightgbm (>=4.5.0,<5.0.0)
Requires-Dist: scikit-learn (>=1.5.2,<2.0.0)
Project-URL: Repository, https://github.com/RektPunk/Imbalance-LightGBM
